Workbook

Sheet Léame
A1: Policentro ficticio de la CSS en Chiriquí: hoja de datos del hito 2
A2: CONSTRUCCIÓN DOCENTE FICTICIA. No son datos de ningún policentro real de la CSS ni del MINSA.
A3: Economía y Finanzas de los Servicios de Salud, UDELAS. Trabajo final guiado, hito 2: oferta, integración y costo.
A5: Qué es | B5: El mismo policentro del escenario de la sesión 04: usted es su director médico y le piden el anteproyecto de presupuesto. Aquí están los datos de un mes para costear sus servicios.
A6: Por qué es ficticio | B6: Para que el método se aprenda sin exponer datos de una institución real. Las cifras son coherentes con el deck S04: la consulta de medicina general cuesta B/. 18 con 80 % fijo; el laboratorio gasta B/. 7,150, 4,675 y 6,490; la enfermera cuesta B/. 2,400 por 7,200 minutos.
A7: Colores | B7: Azul: dato. Negro: fórmula. Verde: vínculo a otra hoja. Amarillo: celda que llena su equipo. La columna gris de la derecha muestra la fórmula de la celda vecina.
A8: Paso a paso | B8: La guía del costeo en orden: primero la asignación escalonada (hoja Reparto), después el TDABC. Empiecen por ahí.
A9: Centros | B9: Los nueve centros de producción, con mano de obra, insumos y gastos generales del mes. Calcula el costo directo.
A10: Bases | B10: Con qué base reparte cada centro administrativo y de apoyo, y cuánto le toca a cada uno.
A11: Reparto | B11: Aquí trabaja su equipo: la asignación escalonada (step down) hasta el costo total y el costo por actividad de los cuatro centros finales.
A12: Laboratorio | B12: El ejemplo del deck S04 y la oferta del laboratorio privado.
A13: TDABC | B13: El costeo por actividades y tiempo de la consulta de crecimiento y desarrollo.
A14: Aseguramiento | B14: Cuántas atenciones fueron a asegurados y a no asegurados. Sirve para la pregunta de quién paga.
A15: Escenarios | B15: Plantilla del costo unitario aplicado a un territorio: escenario actual frente a escenario en red. Cambie los datos azules por los de su territorio del hito 1.
A16: Presupuesto | B16: Presupuesto por programas: meta por costo unitario.
... A18: Ojo | B18: Nunca use la población asegurada como denominador. El policentro de la CSS también atiende a no asegurados.

Sheet Paso a paso
A1: Paso a paso del costeo
A2: CONSTRUCCIÓN DOCENTE FICTICIA. No son datos de ningún policentro real de la CSS ni del MINSA.
A3: Hagan los pasos en orden. Cada ejemplo es solo la primera cuenta: el resto lo calcula su equipo.
A5: A. Asignación escalonada, hoja Reparto
A6: 1 | B6: Ubiquen los tres tipos de centro | C6: En la hoja Centros: administrativos (G1 y G2), de apoyo (A1, A2 y A3) y finales (F1 a F4). Los finales atienden al paciente; los demás les sirven, y su costo tiene que terminar cargado en los finales.
A7: 2 | B7: Lean el costo directo de cada centro | C7: Columna G de la hoja Centros: mano de obra + insumos + gastos generales. Ya está calculado. Ejemplo: Dirección y administración (G1) = 7800 + 400 + 1300 = B/. 9500.
A8: 3 | B8: Repartan G1 por funcionarios | C8: En la hoja Reparto, fila 14 (monto que reparte), columna D: lo que reparte G1 es su costo directo, =C5. En cada celda amarilla de la columna D: monto que reparte × funcionarios del centro ÷ total de funcionarios (43, hoja Bases). Ejemplo: Registros médicos recibe 9500 × 4 ÷ 43 = B/. 883.72. En Excel: =D$14*Bases!C7/Bases!C$14
A9: 4 | B9: Repartan G2 por metros cuadrados | C9: G2 reparte su costo directo más lo que recibió de G1: en E14, =C6+D6. Cada centro recibe ese monto × sus metros cuadrados ÷ el total de metros (hoja Bases, columna D).
A10: 5 | B10: Sigan el mismo orden con A1, A2 y A3 | C10: A1 reparte por atenciones registradas, A2 por recetas despachadas y A3 por pruebas solicitadas. Cada uno reparte su costo directo más todo lo que ya recibió. Un centro que ya repartió no recibe de los que vienen después.
A11: 6 | B11: Costo total de cada centro final | C11: Columna I: costo directo + todo lo que recibió (columnas D a H).
A12: 7 | B12: Costo por actividad | C12: Columna K: costo total ÷ producción del mes (columna J). Es lo que cuesta una consulta o una atención. Escriban la fórmula como texto en la columna N.
A13: 8 | B13: Porcentaje fijo | C13: Columna M: 1 − insumos ÷ costo total. Los insumos son lo variable; el resto es fijo.
A14: 9 | B14: Controlen el reparto | C14: La celda C18 debe decir: Sí, todo el costo llegó a los finales. Si dice No, se perdió o se duplicó costo: revisen la fila 14 y que cada centro reparta lo suyo más lo recibido.
A15: B. Costeo por actividades y tiempo, hoja TDABC
A16: 1 | B16: Costo del minuto de cada recurso | C16: Hoja TDABC, arriba: costo de capacidad del mes ÷ minutos disponibles al mes. Ejemplo: admisión, 1080 ÷ 7200 = B/. 0.15 por minuto.
A17: 2 | B17: Costo de cada actividad | C17: Minutos que toma × costo del minuto del recurso que la hace. Ejemplo: abrir el expediente toma 5 minutos, 5 × 0.15 = B/. 0.75.
A18: 3 | B18: Costo del ciclo completo | C18: Sumen las actividades más los insumos por consulta. Es el costo de la consulta de crecimiento y desarrollo por TDABC.
A19: 4 | B19: Capacidad usada | C19: Minutos usados en el mes ÷ minutos disponibles. Lo que falta para llegar a 100 % es capacidad ociosa: se paga y no se usa.
A20: 5 | B20: Comparen los dos métodos | C20: Pongan al lado el costo por actividad de crecimiento y desarrollo que salió del reparto (paso A7). No dan lo mismo: expliquen por qué en la sección 3.3 del tablero.
A21: 6 | B21: C. Al tablero | C21: Traigan los resultados al tablero: los totales de Centros a 3.1; el directo, el indirecto y el total de cada final a 3.2; y el TDABC a 3.3. Adjunten la hoja trabajada a la entrega en Classroom.

Sheet Centros
A1: Centros de producción y costo directo del mes
A2: CONSTRUCCIÓN DOCENTE FICTICIA. No son datos de ningún policentro real de la CSS ni del MINSA.
A3: Mes de referencia ficticio. Balboas (B/.). Mano de obra: salarios y cuotas patronales. Insumos: medicamentos, material y reactivos. Gastos generales: servicios básicos, mantenimiento, depreciación de equipo.
A4: Código | B4: Centro de producción | C4: Tipo | D4: Mano de obra B/. | E4: Insumos B/. | F4: Gastos generales B/. | G4: Costo directo B/. | H4: Fórmula del costo directo | I4: Producción del mes | J4: Unidad de producción
A5: G1 | B5: Dirección y administración | C5: Administrativo (general) | D5: 7800 | E5: 400 | F5: 1300 | G5: =SUM(D5:F5) | H5: =_xlfn.FORMULATEXT(G5)
A6: G2 | B6: Servicios generales: aseo, mantenimiento y seguridad | C6: Administrativo (general) | D6: 3800 | E6: 900 | F6: 2800 | G6: =SUM(D6:F6) | H6: =_xlfn.FORMULATEXT(G6)
A7: A1 | B7: Registros médicos y estadística | C7: De apoyo (logístico) | D7: 3000 | E7: 200 | F7: 300 | G7: =SUM(D7:F7) | H7: =_xlfn.FORMULATEXT(G7)
A8: A2 | B8: Farmacia | C8: De apoyo (asistencial) | D8: 2400 | E8: 300 | F8: 300 | G8: =SUM(D8:F8) | H8: =_xlfn.FORMULATEXT(G8) | I8: 5100 | J8: recetas despachadas
A9: A3 | B9: Laboratorio clínico | C9: De apoyo (asistencial) | D9: 8875 | E9: 7040 | F9: 2400 | G9: =SUM(D9:F9) | H9: =_xlfn.FORMULATEXT(G9) | I9: 8000 | J9: pruebas
A10: F1 | B10: Consulta de medicina general | C10: Final | D10: 33120 | E10: 14400 | F10: 3323 | G10: =SUM(D10:F10) | H10: =_xlfn.FORMULATEXT(G10) | I10: 4000 | J10: consultas
A11: F2 | B11: Control prenatal | C11: Final | D11: 5640 | E11: 675 | F11: 543 | G11: =SUM(D11:F11) | H11: =_xlfn.FORMULATEXT(G11) | I11: 450 | J11: consultas
A12: F3 | B12: Crecimiento y desarrollo | C12: Final | D12: 6960 | E12: 650 | F12: 213 | G12: =SUM(D12:F12) | H12: =_xlfn.FORMULATEXT(G12) | I12: 650 | J12: consultas
A13: F4 | B13: Urgencias | C13: Final | D13: 22000 | E13: 8000 | F13: 2600 | G13: =SUM(D13:F13) | H13: =_xlfn.FORMULATEXT(G13) | I13: 1200 | J13: atenciones
B14: Total del policentro | D14: =SUM(D5:D13) | E14: =SUM(E5:E13) | F14: =SUM(F5:F13) | G14: =SUM(G5:G13) | H14: =_xlfn.FORMULATEXT(G14)
B16: Distribución por tipo de costo
B17: Mano de obra | C17: =D14/$G$14 | D17: =_xlfn.FORMULATEXT(C17)
B18: Insumos | C18: =E14/$G$14 | D18: =_xlfn.FORMULATEXT(C18)
B19: Gastos generales | C19: =F14/$G$14 | D19: =_xlfn.FORMULATEXT(C19)
B21: Supuesto del curso para separar fijo y variable: en el corto plazo, los insumos directos de cada centro son el costo variable; la mano de obra, los gastos generales y lo que el centro recibe por reparto son fijos.

Sheet Bases
A1: Bases de reparto
A2: CONSTRUCCIÓN DOCENTE FICTICIA. No son datos de ningún policentro real de la CSS ni del MINSA.
A3: Cada columna es un centro que reparte, en el orden del reparto escalonado. La celda dice cuánto de esa base tiene el centro de la fila. En blanco: ese centro no recibe de esa columna.
A4: Código | B4: Centro | C4: G1 reparte por: Funcionarios | D4: G2 reparte por: Metros cuadrados | E4: A1 reparte por: Atenciones registradas | F4: A2 reparte por: Recetas despachadas | G4: A3 reparte por: Pruebas de laboratorio solicitadas
A5: G1 | B5: Dirección y administración
A6: G2 | B6: Servicios generales: aseo, mantenimiento y seguridad | C6: 6
A7: A1 | B7: Registros médicos y estadística | C7: 4 | D7: 40
A8: A2 | B8: Farmacia | C8: 3 | D8: 60
A9: A3 | B9: Laboratorio clínico | C9: 7 | D9: 120
A10: F1 | B10: Consulta de medicina general | C10: 10 | D10: 320 | E10: 4000 | F10: 3600 | G10: 3600
A11: F2 | B11: Control prenatal | C11: 2 | D11: 40 | E11: 450 | F11: 300 | G11: 600
A12: F3 | B12: Crecimiento y desarrollo | C12: 3 | D12: 40 | E12: 650 | F12: 100 | G12: 100
A13: F4 | B13: Urgencias | C13: 8 | D13: 220 | E13: 1200 | F13: 1100 | G13: 3700
B14: Total de la base | C14: =SUM(C5:C13) | D14: =SUM(D5:D13) | E14: =SUM(E5:E13) | F14: =SUM(F5:F13) | G14: =SUM(G5:G13)
B15: Fórmula del total | C15: =_xlfn.FORMULATEXT(C14)
B17: Orden del reparto: primero Dirección (G1), luego Servicios generales (G2), Registros médicos (A1), Farmacia (A2) y Laboratorio (A3). Un centro que ya repartió no recibe de los que vienen después. La base de A1 es la producción de cada final.

Sheet Reparto
A1: Asignación escalonada y costo por actividad
A2: CONSTRUCCIÓN DOCENTE FICTICIA. No son datos de ningún policentro real de la CSS ni del MINSA.
A3: Costo que recibe cada centro = monto que reparte el centro de la columna × base del centro de la fila ÷ total de la base de esa columna.
A4: Código | B4: Centro | C4: Costo directo B/. | D4: Recibe de G1 | E4: Recibe de G2 | F4: Recibe de A1 | G4: Recibe de A2 | H4: Recibe de A3 | I4: Costo total B/. | J4: Producción | K4: Costo por actividad B/. | L4: Insumos (variable) B/. | M4: Porcentaje fijo | N4: Fórmula del costo por actividad
A5: G1 | B5: Dirección y administración | C5: =Centros!G5 | I5: se reparte
A6: G2 | B6: Servicios generales: aseo, mantenimiento y seguridad | C6: =Centros!G6 | I6: se reparte
A7: A1 | B7: Registros médicos y estadística | C7: =Centros!G7 | I7: se reparte
A8: A2 | B8: Farmacia | C8: =Centros!G8 | I8: se reparte
A9: A3 | B9: Laboratorio clínico | C9: =Centros!G9 | I9: se reparte
A10: F1 | B10: Consulta de medicina general | C10: =Centros!G10 | J10: =Centros!I10 | L10: =Centros!E10 | N10: Escriba aquí su fórmula como texto
A11: F2 | B11: Control prenatal | C11: =Centros!G11 | J11: =Centros!I11 | L11: =Centros!E11 | N11: Escriba aquí su fórmula como texto
A12: F3 | B12: Crecimiento y desarrollo | C12: =Centros!G12 | J12: =Centros!I12 | L12: =Centros!E12 | N12: Escriba aquí su fórmula como texto
A13: F4 | B13: Urgencias | C13: =Centros!G13 | J13: =Centros!I13 | L13: =Centros!E13 | N13: Escriba aquí su fórmula como texto
B14: Monto que reparte el centro de la columna
B16: Control 1. Costo directo de todo el policentro | C16: =SUM(C5:C13)
B17: Control 2. Suma de los costos totales de los cuatro finales | C17: =SUM(I10:I13) | G17: =_xlfn.FORMULATEXT(C17)
B18: ¿Cuadra el reparto? | C18: =IF(ABS(C16-C17)<0.5,"Sí: todo el costo llegó a los finales","No: revise el reparto")
B20: Cómo llenarlo. 1) En la fila del monto que reparte, sume el costo directo del centro de la columna más lo que ya recibió. 2) En cada celda amarilla de la columna: monto que reparte × base del centro ÷ total de la base (hoja Bases). 3) Costo total = costo directo + todo lo recibido. 4) Costo por actividad = costo total ÷ producción. 5) Porcentaje fijo = 1 − insumos ÷ costo total. Ejemplo de la primera celda: Registros médicos recibe de G1 = monto de G1 × 4 ÷ 43.

Sheet Laboratorio
A1: El laboratorio del policentro: el ejemplo del deck S04
A2: CONSTRUCCIÓN DOCENTE FICTICIA. No son datos de ningún policentro real de la CSS ni del MINSA.
A3: Costo promedio = gasto del mes ÷ pruebas del mes. Química: el laboratorio privado ofrece la prueba a B/. 1.90.
A4: Prueba | B4: Mano de obra B/. | C4: Insumos B/. | D4: Gastos generales B/. | E4: Gasto del mes B/. | F4: Pruebas | G4: Costo promedio B/. | H4: Fórmula
A5: Urinálisis | B5: 3900 | C5: 2350 | D5: 900 | E5: =SUM(B5:D5) | F5: 2800 | G5: =E5/F5 | H5: =_xlfn.FORMULATEXT(G5)
A6: Química | B6: 1975 | C6: 2000 | D6: 700 | E6: =SUM(B6:D6) | F6: 2200 | G6: =E6/F6 | H6: =_xlfn.FORMULATEXT(G6)
A7: Serología | B7: 3000 | C7: 2690 | D7: 800 | E7: =SUM(B7:D7) | F7: 3000 | G7: =E7/F7 | H7: =_xlfn.FORMULATEXT(G7)
A8: Total | B8: =SUM(B5:B7) | C8: =SUM(C5:C7) | D8: =SUM(D5:D7) | E8: =SUM(E5:E7) | F8: =SUM(F5:F7) | G8: =E8/F8
A9: ¿Cuadra con el costo directo del laboratorio en Centros? | E9: =IF(ABS(E8-Centros!G9)<0.01,"Sí","No")
A11: La oferta del laboratorio privado para la química
A12: Precio por prueba del privado B/. | B12: 1.9
A13: Pruebas de química del mes | B13: =F6 | C13: =_xlfn.FORMULATEXT(B13)
A14: Lo que desaparece si se compra afuera: insumos B/. | B14: =C6 | C14: =_xlfn.FORMULATEXT(B14)
A15: Lo que se queda: mano de obra y gastos generales B/. | B15: =B6+D6 | C15: =_xlfn.FORMULATEXT(B15)
A16: Producir adentro B/. | B16: =E6 | C16: =_xlfn.FORMULATEXT(B16)
A17: Comprar afuera más lo fijo que se queda B/. | B17: =B12*B13+B15 | C17: =_xlfn.FORMULATEXT(B17)
A18: Diferencia al mes B/. | B18: =B17-B16 | C18: =_xlfn.FORMULATEXT(B18)
A20: Pregunta del deck S04: ¿cierra la química y la compra afuera? Solo conviene si el personal y el espacio se reasignan.

Sheet TDABC
A1: Costeo por actividades y tiempo: consulta de crecimiento y desarrollo
A2: CONSTRUCCIÓN DOCENTE FICTICIA. No son datos de ningún policentro real de la CSS ni del MINSA.
A3: Dos números por recurso: cuánto cuesta su minuto y cuántos minutos toma cada actividad. Costo del minuto = costo de capacidad ÷ minutos disponibles.
A4: Recurso | B4: Costo de capacidad del mes B/. | C4: Minutos disponibles al mes | D4: Costo del minuto B/. | E4: Fórmula
A5: Admisión y registros médicos | B5: 1080 | C5: 7200 | D5: =B5/C5 | E5: =_xlfn.FORMULATEXT(D5)
A6: Enfermería | B6: 2400 | C6: 7200 | D6: =B6/C6 | E6: =_xlfn.FORMULATEXT(D6)
A7: Médico general | B7: 4320 | C7: 7200 | D7: =B7/C7 | E7: =_xlfn.FORMULATEXT(D7)
A8: Minutos disponibles: 150 horas de trabajo al mes menos pausas, reuniones y capacitación, por persona. Enfermería: B/. 2,400 por 7,200 minutos, como en el deck S04.
A10: Actividad del proceso, de la llegada a la salida | B10: Recurso | C10: Minutos por consulta | D10: Costo del minuto B/. | E10: Costo de la actividad B/. | F10: Fórmula
A11: Admisión y apertura del expediente | B11: =A5 | C11: 5 | D11: =D5 | E11: =C11*D11 | F11: =_xlfn.FORMULATEXT(E11)
A12: Preconsulta: peso, talla, perímetro y vacunas | B12: =A6 | C12: 20 | D12: =D6 | E12: =C12*D12 | F12: =_xlfn.FORMULATEXT(E12)
A13: Valoración médica | B13: =A7 | C13: 5 | D13: =D7 | E13: =C13*D13 | F13: =_xlfn.FORMULATEXT(E13)
A14: Insumos por consulta (material y biológicos no cubiertos por el programa) | E14: 1
A15: Costo del ciclo completo por TDABC | E15: =SUM(E11:E14) | F15: =_xlfn.FORMULATEXT(E15)
A17: Capacidad usada | B17: Consultas del mes | C17: Minutos usados | D17: Minutos disponibles | E17: Capacidad usada | F17: Fórmula
A18: Enfermería (2 personas) | B18: =Centros!I12 | C18: =B18*C12 | D18: =C6*2 | E18: =C18/D18 | F18: =_xlfn.FORMULATEXT(E18)
A19: Médico general (media jornada) | B19: =Centros!I12 | C19: =B19*C13 | D19: =C7*0.5 | E19: =C19/D19 | F19: =_xlfn.FORMULATEXT(E19)
A21: Su equipo compara este costo con el costo por actividad de crecimiento y desarrollo que sale del reparto escalonado. No dan lo mismo: expliquen por qué.

Sheet Aseguramiento
A1: Quién recibió la atención: asegurados y no asegurados
A2: CONSTRUCCIÓN DOCENTE FICTICIA. No son datos de ningún policentro real de la CSS ni del MINSA.
A3: El policentro es de la CSS, pero en provincia atiende también a no asegurados. Esta hoja calcula cuánto cuesta esa atención; quién la paga hoy, lo investiga su equipo con fuente.
A4: Centro final | B4: Atenciones a asegurados | C4: Atenciones a no asegurados | D4: Total | E4: Porcentaje no asegurado | F4: Costo por actividad B/. | G4: Costo de la atención a no asegurados B/. | H4: Fórmula
A5: Consulta de medicina general | B5: 3240 | C5: 760 | D5: =B5+C5 | E5: =IF(D5>0,C5/D5,0) | F5: =Reparto!K10 | G5: =C5*F5 | H5: =_xlfn.FORMULATEXT(G5)
A6: Control prenatal | B6: 315 | C6: 135 | D6: =B6+C6 | E6: =IF(D6>0,C6/D6,0) | F6: =Reparto!K11 | G6: =C6*F6 | H6: =_xlfn.FORMULATEXT(G6)
A7: Crecimiento y desarrollo | B7: 455 | C7: 195 | D7: =B7+C7 | E7: =IF(D7>0,C7/D7,0) | F7: =Reparto!K12 | G7: =C7*F7 | H7: =_xlfn.FORMULATEXT(G7)
A8: Urgencias | B8: 900 | C8: 300 | D8: =B8+C8 | E8: =IF(D8>0,C8/D8,0) | F8: =Reparto!K13 | G8: =C8*F8 | H8: =_xlfn.FORMULATEXT(G8)
A9: Total del mes | B9: =SUM(B5:B8) | C9: =SUM(C5:C8) | D9: =SUM(D5:D8) | G9: =SUM(G5:G8)
A10: Al año (× 12) | G10: =G9*12 | H10: =_xlfn.FORMULATEXT(G10)
A12: ¿Cuánto recupera hoy la CSS por esa atención, y de quién? Fuente:
A13: Monto recuperado al mes B/. (si lo encuentran)
A15: Investíguenlo con fuente: convenio o compensación de costos entre el MINSA y la CSS, cobro al paciente, o nadie. No afirmen una cifra sin su fuente.
A16: La columna de costo por actividad se llena sola cuando su equipo termine la hoja Reparto.

Sheet Escenarios
A1: El costo unitario aplicado al territorio: escenario actual frente a escenario en red
A2: CONSTRUCCIÓN DOCENTE FICTICIA. No son datos de ningún policentro real de la CSS ni del MINSA.
A3: Ejemplo con hipertensión arterial. Cambie los datos azules por los de su territorio del hito 1 y cite cada fuente en el tablero. El denominador es la población del territorio.
A4: Dato o cálculo | B4: Valor | C4: Fórmula o fuente
A5: Población del territorio (denominador) | B5: 480000 | C5: Del hito 1. Ejemplo ficticio.
A6: Proporción de adultos de 20 años y más | B6: 0.62 | C6: Del hito 1, pirámide. Ejemplo ficticio.
A7: Prevalencia de hipertensión en adultos | B7: 0.3 | C7: Encuesta con año. Ejemplo ficticio.
A8: Personas con hipertensión en el territorio | B8: =B5*B6*B7 | C8: =_xlfn.FORMULATEXT(B8)
A9: Proporción en control en la red pública | B9: 0.35 | C9: Ejemplo ficticio.
A10: Pacientes en control | B10: =B8*B9 | C10: =_xlfn.FORMULATEXT(B10)
A11: Consultas por paciente al año | B11: 4 | C11: Norma o guía de manejo.
A12: Consultas al año | B12: =B10*B11 | C12: =_xlfn.FORMULATEXT(B12)
A13: Costo por consulta en medicina general B/. | B13: =IF(Reparto!K10>0,Reparto!K10,18) | C13: Del reparto; si aún está vacío, el B/. 18 del deck S04.
A14: Costo por atención en urgencias B/. | B14: =IF(Reparto!K13>0,Reparto!K13,40) | C14: Del reparto; si aún está vacío, B/. 40 provisional.
A15: ESCENARIO ACTUAL: proporción de atenciones que ocurren en urgencias | B15: 0.3 | C15: Supuesto que su equipo debe sostener.
A16: Costo anual actual B/. | B16: =B12*(B15*B14+(1-B15)*B13) | C16: =_xlfn.FORMULATEXT(B16)
A17: ESCENARIO EN RED: proporción en urgencias con primer nivel resolutivo | B17: 0.1 | C17: Meta de la propuesta.
A18: Costo anual en red B/. | B18: =B12*(B17*B14+(1-B17)*B13) | C18: =_xlfn.FORMULATEXT(B18)
A19: Diferencia anual B/. | B19: =B16-B18 | C19: =_xlfn.FORMULATEXT(B19)
A20: Costo por paciente en control al año, actual B/. | B20: =IF(B10>0,B16/B10,0) | C20: =_xlfn.FORMULATEXT(B20)
A21: Costo por paciente en control al año, en red B/. | B21: =IF(B10>0,B18/B10,0) | C21: =_xlfn.FORMULATEXT(B21)
A23: Supuesto que la IA suele proponer mal: usar la población asegurada como denominador. Aquí el denominador es la población del territorio.

Sheet Presupuesto
A1: Presupuesto por programas: meta por costo unitario
A2: CONSTRUCCIÓN DOCENTE FICTICIA. No son datos de ningún policentro real de la CSS ni del MINSA.
A3: Los tres programas del deck S04 como ejemplo. Su equipo agrega los programas de su propuesta con su meta y su costo unitario.
A4: Programa | B4: Meta anual | C4: Unidad | D4: Costo unitario B/. | E4: Presupuesto B/. | F4: Fórmula | G4: De dónde sale el costo unitario
A5: Control prenatal | B5: 1200 | C5: consultas | D5: 22 | E5: =B5*D5 | F5: =_xlfn.FORMULATEXT(E5) | G5: Reparto, control prenatal
A6: Crecimiento y desarrollo | B6: 2000 | C6: consultas | D6: 15 | E6: =B6*D6 | F6: =_xlfn.FORMULATEXT(E6) | G6: Reparto, crecimiento y desarrollo
A7: Adulto con hipertensión | B7: 3600 | C7: consultas | D7: 18 | E7: =B7*D7 | F7: =_xlfn.FORMULATEXT(E7) | G7: Reparto, medicina general
A8: Programa de su propuesta | E8: =B8*D8 | F8: =_xlfn.FORMULATEXT(E8)
A9: Programa de su propuesta | E9: =B9*D9 | F9: =_xlfn.FORMULATEXT(E9)
A10: Total del anteproyecto | E10: =SUM(E5:E9) | F10: =_xlfn.FORMULATEXT(E10)
A12: Compare con la propuesta del administrador del escenario: lo ejecutado el año anterior más 5 %. ¿Qué le falta a esa propuesta que esta tabla sí tiene?
